SpringBootCookbookZhongwenban/README.md
SpringBootCookbookZhongwenban/__init__.py
SpringBootCookbookZhongwenban/__main__.py
SpringBootCookbookZhongwenban/file.epub
SpringBootCookbookZhongwenban/index.html
SpringBootCookbookZhongwenban/css/__init__.py
SpringBootCookbookZhongwenban/css/annotations.css
SpringBootCookbookZhongwenban/css/main.css
SpringBootCookbookZhongwenban/css/normalize.css
SpringBootCookbookZhongwenban/css/popup.css
SpringBootCookbookZhongwenban/font/__init__.py
SpringBootCookbookZhongwenban/font/fontello.eot
SpringBootCookbookZhongwenban/font/fontello.svg
SpringBootCookbookZhongwenban/font/fontello.ttf
SpringBootCookbookZhongwenban/font/fontello.woff
SpringBootCookbookZhongwenban/img/__init__.py
SpringBootCookbookZhongwenban/img/annotator-glyph-sprite.png
SpringBootCookbookZhongwenban/img/annotator-icon-sprite.png
SpringBootCookbookZhongwenban/img/apple-touch-icon.png
SpringBootCookbookZhongwenban/img/cancelfullscreen.png
SpringBootCookbookZhongwenban/img/close.png
SpringBootCookbookZhongwenban/img/fullscreen.png
SpringBootCookbookZhongwenban/img/loader.gif
SpringBootCookbookZhongwenban/img/menu-icon.png
SpringBootCookbookZhongwenban/img/save.png
SpringBootCookbookZhongwenban/img/saved.png
SpringBootCookbookZhongwenban/img/settings-s.png
SpringBootCookbookZhongwenban/img/settings.png
SpringBootCookbookZhongwenban/img/star.png
SpringBootCookbookZhongwenban/js/__init__.py
SpringBootCookbookZhongwenban/js/epub.js
SpringBootCookbookZhongwenban/js/epub.min.js
SpringBootCookbookZhongwenban/js/epub.min.map
SpringBootCookbookZhongwenban/js/hooks.min.js
SpringBootCookbookZhongwenban/js/hooks.min.map
SpringBootCookbookZhongwenban/js/reader.js
SpringBootCookbookZhongwenban/js/reader.js.map
SpringBootCookbookZhongwenban/js/reader.min.js
SpringBootCookbookZhongwenban/js/reader.min.map
SpringBootCookbookZhongwenban/js/hooks/__init__.py
SpringBootCookbookZhongwenban/js/hooks/extensions/__init__.py
SpringBootCookbookZhongwenban/js/hooks/extensions/highlight.js
spring_boot_cookbook_zhongwenban-2024.3.4.0.dist-info/METADATA
spring_boot_cookbook_zhongwenban-2024.3.4.0.dist-info/WHEEL
spring_boot_cookbook_zhongwenban-2024.3.4.0.dist-info/entry_points.txt
spring_boot_cookbook_zhongwenban-2024.3.4.0.dist-info/top_level.txt
spring_boot_cookbook_zhongwenban-2024.3.4.0.dist-info/RECORD
